{
  "status": true,
  "data": {
    "brand": "",
    "model": "Nokia 7610 Supernova",
    "imageUrl": "https://fdn2.gsmarena.com/vv/pics/nokia/nokia-7610-01.jpg",
    "device_images": [
      {
        "color": "Default",
        "url": "https://fdn2.gsmarena.com/vv/bigpic/nokia-7610-s.jpg"
      }
    ],
    "siblingDeviceSlugs": [],
    "release_date": "Released 2008, August",
    "dimensions": "99g, 15mm thickness",
    "os": "Feature phone",
    "storage": "64MB storage, microSD slot",
    "specifications": {
      "Network": {
        "Technology": "<a href=\"#\" class=\"link-network-detail collapse\" data-spec=\"nettech\">GSM</a>",
        "2G bands": "GSM 850 / 900 / 1800 / 1900",
        "GPRS": "Class 32",
        "EDGE": "Class 32"
      },
      "Launch": {
        "Announced": "2008, June. Released 2008, August",
        "Status": "Discontinued"
      },
      "Body": {
        "Dimensions": "98 x 48 x 15 mm, 63 cc (3.86 x 1.89 x 0.59 in)",
        "Weight": "99 g (3.49 oz)",
        "SIM": "Mini-SIM"
      },
      "Display": {
        "Type": "TFT, 16M colors",
        "Size": "2.0 inches, 12.4 cm<sup>2</sup> (~26.3% screen-to-body ratio)",
        "Resolution": "240 x 320 pixels, 4:3 ratio (~200 ppi density)"
      },
      "Memory": {
        "Card slot": "microSD (dedicated slot), 512 MB included",
        "Phonebook": "2000 entries , Photocall",
        "Call records": "20 dialed, 20 received, 20 missed calls",
        "Internal": "64MB"
      },
      "Main Camera": {
        "Single": "3.15 MP, AF",
        "Features": "Dual-LED",
        "Video": "480p@15fps"
      },
      "Selfie camera": {
        "Features": "No"
      },
      "Sound": {
        "Loudspeaker": "Yes",
        "Alert types": "Vibration; Downloadable polyphonic, MP3 ringtones",
        "3.5mm jack": "No",
        "Features": "2.5 mm audio jack"
      },
      "Comms": {
        "WLAN": "No",
        "Bluetooth": "2.0, A2DP",
        "Positioning": "No",
        "Radio": "Stereo FM radio, RDS",
        "USB": "microUSB 2.0"
      },
      "Features": {
        "Sensors": "",
        "Messaging": "SMS, MMS, Email, IM",
        "Browser": "WAP 2.0/xHTML, HTML, Adobe Flash Lite",
        "Games": "Yes",
        "Java": "Yes, MIDP 2.1",
        "Features": "Xpress-on covers\n\nMP4/H.264 player\n\nMP3/eAAC+/WMA player\n\nOrganizer\n\nPush to talk\n\nVoice memo\n\nPredictive text input"
      },
      "Battery": {
        "Type": "Removable Li-Ion 860 mAh battery (BL-4S)",
        "Stand-by": "Up to 288 h",
        "Talk time": "Up to 6 h 40 min"
      },
      "Misc": {
        "Colors": "Muted Gray, Steel Blue, Red, Bright Lilac, Pristine White, Graphite, Passionate Purple",
        "SAR": "0.81 W/kg (head) &nbsp; &nbsp; 0.65 W/kg (body) &nbsp; &nbsp;",
        "SAR EU": "0.66 W/kg (head) &nbsp; &nbsp;",
        "Price": "About 100 EUR"
      }
    },
    "picturesPageData": {
      "officialImages": [
        "https://fdn2.gsmarena.com/vv/pics/nokia/nokia-7610-01.jpg",
        "https://fdn2.gsmarena.com/vv/pics/nokia/nokia-7610-02.jpg"
      ],
      "colorVariants": [],
      "picturesPageUrl": "https://www.gsmarena.com/nokia_7610_supernova-pictures-2444.php"
    }
  }
}