{
  "status": true,
  "data": {
    "brand": "",
    "model": "Motorola CUPE",
    "imageUrl": "https://fdn2.gsmarena.com/vv/pics/motorola/motorola-cupe-1.jpg",
    "device_images": [
      {
        "color": "Default",
        "url": "https://fdn2.gsmarena.com/vv/bigpic/motorola-cupe.jpg"
      }
    ],
    "siblingDeviceSlugs": [],
    "release_date": "Released 2010, December",
    "dimensions": "115g, 14.4mm thickness",
    "os": "Feature phone",
    "storage": "microSD slot",
    "specifications": {
      "Network": {
        "Technology": "<a href=\"#\" class=\"link-network-detail collapse\" data-spec=\"nettech\">GSM / HSPA</a>",
        "2G bands": "GSM 850 / 900 / 1800 / 1900",
        "3G bands": "HSDPA 900 / 2100",
        "Speed": "HSPA 7.2/0.384 Mbps"
      },
      "Launch": {
        "Announced": "2010, September. Released 2010, December",
        "Status": "Discontinued"
      },
      "Body": {
        "Dimensions": "107.8 x 53 x 14.4 mm (4.24 x 2.09 x 0.57 in)",
        "Weight": "115 g (4.06 oz)",
        "SIM": "Mini-SIM"
      },
      "Display": {
        "Type": "TFT,  256K colors",
        "Size": "2.4 inches, 17.8 cm<sup>2</sup> (~31.2% screen-to-body ratio)",
        "Resolution": "240 x 320 pixels, 4:3 ratio (~167 ppi density)",
        "Features": "secondary external display"
      },
      "Memory": {
        "Card slot": "microSD (dedicated slot)",
        "Phonebook": "Yes, Photocall",
        "Call records": "Yes"
      },
      "Main Camera": {
        "Single": "3.15 MP",
        "Video": "No"
      },
      "Selfie camera": {
        "Features": "No"
      },
      "Sound": {
        "Loudspeaker": "Yes",
        "3.5mm jack": "No"
      },
      "Comms": {
        "WLAN": "No",
        "Bluetooth": "2.0, A2DP",
        "Positioning": "No",
        "Radio": "No",
        "USB": "microUSB 2.0"
      },
      "Features": {
        "Sensors": "",
        "Messaging": "SMS, MMS, Email",
        "Browser": "HTML",
        "Games": "Yes + downloadable",
        "Java": "Yes, MIDP 2.0",
        "Features": "T-DMB TV tuner\n\nMP3/WAV/AAC+ player\n\nMP4/H.264 player\n\nOrganizer\n\nVoice memo\n\nPredictive text input"
      },
      "Battery": {
        "Type": "Removable Li-Ion 950 mAh battery",
        "Stand-by": "Up to 290 h",
        "Talk time": "Up to 4 h"
      },
      "Misc": {
        "Colors": "Black",
        "Price": "About 150 EUR"
      }
    },
    "picturesPageData": {
      "officialImages": [
        "https://fdn2.gsmarena.com/vv/pics/motorola/motorola-cupe-1.jpg"
      ],
      "colorVariants": [],
      "picturesPageUrl": "https://www.gsmarena.com/motorola_cupe-pictures-3526.php"
    }
  }
}